LICENSE.txt
MANIFEST.in
README.md
setup.cfg
setup.py
yibanApi/__init__.py
yibanApi/config.py
yibanApi/yibanApi.py
yibanApi.egg-info/PKG-INFO
yibanApi.egg-info/SOURCES.txt
yibanApi.egg-info/dependency_links.txt
yibanApi.egg-info/top_level.txt